README.txt
setup.py
TurboJinja.egg-info/PKG-INFO
TurboJinja.egg-info/SOURCES.txt
TurboJinja.egg-info/dependency_links.txt
TurboJinja.egg-info/entry_points.txt
TurboJinja.egg-info/not-zip-safe
TurboJinja.egg-info/paster_plugins.txt
TurboJinja.egg-info/requires.txt
TurboJinja.egg-info/sqlobject.txt
TurboJinja.egg-info/top_level.txt
turbojinja/__init__.py
turbojinja/release.py
turbojinja/widgets.py
