Metadata-Version: 1.0
Name: TurboJinja
Version: 0.9.1
Summary: Jinja(Django & Smarty-like) template for TurboGears
Home-page: http://turbogears.org/cogbin
Author: Fred Lin
Author-email: gasolin+turbogears@gmail.com
License: MIT
Download-URL: http://sourceforge.net/project/showfiles.php?group_id=169297
Keywords: python.templating.engines
Platform: UNKNOWN
Classifier: Development Status :: 3 - Alpha
Classifier: Operating System :: OS Independent
Classifier: Programming Language :: Python
Classifier: Topic :: Software Development :: Libraries :: Python Modules
Classifier: Framework :: TurboGears
